{
  "openapi": "3.1.0",
  "info": {
    "title": "Notification Service",
    "version": "0.1.0"
  },
  "paths": {
    "/health": {
      "get": {
        "tags": [
          "Observability"
        ],
        "summary": "Health",
        "operationId": "health_health_get",
        "responses": {
          "200": {
            "description": "Successful Response",
            "content": {
              "application/json": {
                "schema": {
                  "additionalProperties": {
                    "type": "string"
                  },
                  "type": "object",
                  "title": "Response Health Health Get"
                }
              }
            }
          }
        }
      }
    },
    "/ready": {
      "get": {
        "tags": [
          "Observability"
        ],
        "summary": "Ready",
        "operationId": "ready_ready_get",
        "responses": {
          "200": {
            "description": "Successful Response",
            "content": {
              "application/json": {
                "schema": {
                  "additionalProperties": {
                    "type": "string"
                  },
                  "type": "object",
                  "title": "Response Ready Ready Get"
                }
              }
            }
          }
        }
      }
    },
    "/api/v1/notifications": {
      "post": {
        "tags": [
          "Notifications"
        ],
        "summary": "Send Notification",
        "operationId": "send_notification_api_v1_notifications_post",
        "parameters": [
          {
            "name": "Idempotency-Key",
            "in": "header",
            "required": false,
            "schema": {
              "anyOf": [
                {
                  "type": "string"
                },
                {
                  "type": "null"
                }
              ],
              "title": "Idempotency-Key"
            }
          },
          {
            "name": "X-Tenant-ID",
            "in": "header",
            "required": false,
            "schema": {
              "anyOf": [
                {
                  "type": "string"
                },
                {
                  "type": "null"
                }
              ],
              "title": "X-Tenant-Id"
            }
          }
        ],
        "requestBody": {
          "required": true,
          "content": {
            "application/json": {
              "schema": {
                "$ref": "#/components/schemas/SendNotificationRequest"
              }
            }
          }
        },
        "responses": {
          "202": {
            "description": "Successful Response",
            "content": {
              "application/json": {
                "schema": {
                  "$ref": "#/components/schemas/NotificationReceipt"
                }
              }
            }
          },
          "422": {
            "description": "Validation Error",
            "content": {
              "application/json": {
                "schema": {
                  "$ref": "#/components/schemas/HTTPValidationError"
                }
              }
            }
          }
        }
      }
    },
    "/api/v1/notifications/{notification_id}": {
      "get": {
        "tags": [
          "Notifications"
        ],
        "summary": "Get Notification",
        "operationId": "get_notification_api_v1_notifications__notification_id__get",
        "parameters": [
          {
            "name": "notification_id",
            "in": "path",
            "required": true,
            "schema": {
              "type": "string",
              "format": "uuid",
              "title": "Notification Id"
            }
          },
          {
            "name": "X-Tenant-ID",
            "in": "header",
            "required": false,
            "schema": {
              "anyOf": [
                {
                  "type": "string"
                },
                {
                  "type": "null"
                }
              ],
              "title": "X-Tenant-Id"
            }
          }
        ],
        "responses": {
          "200": {
            "description": "Successful Response",
            "content": {
              "application/json": {
                "schema": {
                  "$ref": "#/components/schemas/NotificationReceipt"
                }
              }
            }
          },
          "422": {
            "description": "Validation Error",
            "content": {
              "application/json": {
                "schema": {
                  "$ref": "#/components/schemas/HTTPValidationError"
                }
              }
            }
          }
        }
      }
    },
    "/metrics": {
      "get": {
        "summary": "Metrics",
        "description": "Endpoint that serves Prometheus metrics.",
        "operationId": "metrics_metrics_get",
        "responses": {
          "200": {
            "description": "Successful Response",
            "content": {
              "application/json": {
                "schema": {}
              }
            }
          }
        }
      }
    }
  },
  "components": {
    "schemas": {
      "HTTPValidationError": {
        "properties": {
          "detail": {
            "items": {
              "$ref": "#/components/schemas/ValidationError"
            },
            "type": "array",
            "title": "Detail"
          }
        },
        "type": "object",
        "title": "HTTPValidationError"
      },
      "NotificationReceipt": {
        "properties": {
          "id": {
            "type": "string",
            "format": "uuid",
            "title": "Id"
          },
          "status": {
            "type": "string",
            "title": "Status"
          },
          "channel": {
            "anyOf": [
              {
                "type": "string"
              },
              {
                "type": "null"
              }
            ],
            "title": "Channel"
          },
          "template_id": {
            "anyOf": [
              {
                "type": "string"
              },
              {
                "type": "null"
              }
            ],
            "title": "Template Id"
          },
          "created_at": {
            "type": "string",
            "format": "date-time",
            "title": "Created At"
          },
          "delivered_at": {
            "anyOf": [
              {
                "type": "string",
                "format": "date-time"
              },
              {
                "type": "null"
              }
            ],
            "title": "Delivered At"
          }
        },
        "type": "object",
        "required": [
          "id",
          "status",
          "created_at"
        ],
        "title": "NotificationReceipt"
      },
      "RecipientSchema": {
        "properties": {
          "address": {
            "type": "string",
            "title": "Address"
          },
          "name": {
            "anyOf": [
              {
                "type": "string"
              },
              {
                "type": "null"
              }
            ],
            "title": "Name"
          }
        },
        "type": "object",
        "required": [
          "address"
        ],
        "title": "RecipientSchema"
      },
      "SendNotificationRequest": {
        "properties": {
          "channel": {
            "type": "string",
            "title": "Channel"
          },
          "template_id": {
            "type": "string",
            "title": "Template Id"
          },
          "recipient": {
            "$ref": "#/components/schemas/RecipientSchema"
          },
          "payload": {
            "additionalProperties": true,
            "type": "object",
            "title": "Payload"
          }
        },
        "type": "object",
        "required": [
          "channel",
          "template_id",
          "recipient",
          "payload"
        ],
        "title": "SendNotificationRequest"
      },
      "ValidationError": {
        "properties": {
          "loc": {
            "items": {
              "anyOf": [
                {
                  "type": "string"
                },
                {
                  "type": "integer"
                }
              ]
            },
            "type": "array",
            "title": "Location"
          },
          "msg": {
            "type": "string",
            "title": "Message"
          },
          "type": {
            "type": "string",
            "title": "Error Type"
          },
          "input": {
            "title": "Input"
          },
          "ctx": {
            "type": "object",
            "title": "Context"
          }
        },
        "type": "object",
        "required": [
          "loc",
          "msg",
          "type"
        ],
        "title": "ValidationError"
      }
    }
  }
}
